{"access_token": "ya29.Gl1TBvQPvdehgCmZJ1GinOBIwI5OSNdNsg27cC88etavfRGZwvkRaC6ydYu2B9gRD5zFF52scwk39ogsghdHX7NQ8oSDrEBAJ594aIaRJopAvRWbBZicj4RbcMKc6kk", "client_id": "973858506946-6jfb7r8rllg982clrqjfubjhdsot36rj.apps.googleusercontent.com", "client_secret": "96ii76T6k5cyiIb6baMNvvSx", "refresh_token": "1/QSspCnCtHKWms7socSNBjN3Xt8tKnkVk559LBrULzyw", "token_expiry": "2018-11-13T10:25:11Z", "token_uri": "https://accounts.google.com/o/oauth2/token", "user_agent": null, "revoke_uri": "https://accounts.google.com/o/oauth2/revoke", "id_token": null, "id_token_jwt": null, "token_response": {"access_token": "ya29.Gl1TBvQPvdehgCmZJ1GinOBIwI5OSNdNsg27cC88etavfRGZwvkRaC6ydYu2B9gRD5zFF52scwk39ogsghdHX7NQ8oSDrEBAJ594aIaRJopAvRWbBZicj4RbcMKc6kk", "expires_in": 3600, "scope": "https://www.googleapis.com/auth/drive.file https://www.googleapis.com/auth/drive.appdata", "token_type": "Bearer"}, "scopes": ["https://www.googleapis.com/auth/drive.appfolder", "https://www.googleapis.com/auth/drive.file"], "token_info_uri": "https://www.googleapis.com/oauth2/v3/tokeninfo", "invalid": false, "_class": "OAuth2Credentials", "_module": "oauth2client.client"}